openSeSSHIAMe/COPYING
openSeSSHIAMe/README.md
openSeSSHIAMe/__about__.py
openSeSSHIAMe/__init__.py
openSeSSHIAMe/openSeSSHIAMe.py
openSeSSHIAMe/etc/openSeSSHIAMe-config.json
openSeSSHIAMe/etc/openSeSSHIAMe-oneshot.service
openSeSSHIAMe/etc/openSeSSHIAMe-oneshot.timer
openSeSSHIAMe-0.1.0.dist-info/COPYING
openSeSSHIAMe-0.1.0.dist-info/METADATA
openSeSSHIAMe-0.1.0.dist-info/WHEEL
openSeSSHIAMe-0.1.0.dist-info/entry_points.txt
openSeSSHIAMe-0.1.0.dist-info/top_level.txt
openSeSSHIAMe-0.1.0.dist-info/RECORD
