Metadata-Version: 2.1
Name: openSeSSHIAMe
Version: 0.1.0
Summary: openSeSSHIAMe allows SSH access to an instance behind the
Home-page: https://gitlab.com/vedvyas/openSeSSHIAMe
Author: Ved Vyas
Author-email: ved@vyas.io
License: MIT
Download-URL: https://gitlab.com/vedvyas/openSeSSHIAMe/repository/archive.tar.bz2?ref=v0.1.0
Keywords: AWS IAM SSH security-group boto3
Platform: UNKNOWN
Classifier: Development Status :: 4 - Beta
Classifier: Intended Audience :: Developers
Classifier: Topic :: System :: Networking
Classifier: License :: OSI Approved :: MIT License
Classifier: Programming Language :: Python :: 3
Requires-Dist: boto3 (>=1.9.121)
Requires-Dist: docopt (>=0.6.2)
Requires-Dist: requests (>=2.21.0)
